sphinxcontrib_yamcs-1.2.13-py3.12-nspkg.pth
sphinxcontrib/yamcs/__init__.py
sphinxcontrib/yamcs/autogen.py
sphinxcontrib/yamcs/color.py
sphinxcontrib/yamcs/fulltoc.py
sphinxcontrib/yamcs/javadoc.py
sphinxcontrib/yamcs/lexers.py
sphinxcontrib/yamcs/opi.py
sphinxcontrib/yamcs/options.py
sphinxcontrib/yamcs/proto.py
sphinxcontrib/yamcs/protoparse.py
sphinxcontrib/yamcs/templates.py
sphinxcontrib_yamcs-1.2.13.dist-info/LICENSE
sphinxcontrib_yamcs-1.2.13.dist-info/METADATA
sphinxcontrib_yamcs-1.2.13.dist-info/WHEEL
sphinxcontrib_yamcs-1.2.13.dist-info/namespace_packages.txt
sphinxcontrib_yamcs-1.2.13.dist-info/top_level.txt
sphinxcontrib_yamcs-1.2.13.dist-info/RECORD
