Metadata-Version: 2.1
Name: sphinxcontrib-yamcs
Version: 1.2.13
Summary: Sphinx extensions for use within the Yamcs project.
Home-page: https://github.com/yamcs/sphinxcontrib-yamcs
Author: Space Applications Services
Author-email: yamcs@spaceapplications.com
License: BSD
Platform: any
Classifier: Framework :: Sphinx :: Extension
Classifier: Intended Audience :: Developers
Requires-Python: >=3.7
License-File: LICENSE
Requires-Dist: yamcs-client
Requires-Dist: Sphinx>=4.0.0
Requires-Dist: pyyaml
